searxng_search/__init__.py
searxng_search/exceptions.py
searxng_search/searxng_search.py
searxng_search/utils.py
searxng_search-0.1.2.dist-info/licenses/LICENSE.md
test/demo.py
searxng_search-0.1.2.dist-info/METADATA
searxng_search-0.1.2.dist-info/WHEEL
searxng_search-0.1.2.dist-info/top_level.txt
searxng_search-0.1.2.dist-info/RECORD
