Metadata-Version: 2.4
Name: searxng_search
Version: 0.1.2
Summary: A Python client for interacting with local/LAN SearXNG instances.
Author-email: JamePeng <jame_peng@sina.com>
License-Expression: MIT
Project-URL: Homepage, https://github.com/JamePeng/searxng_search
Project-URL: Bug Tracker, https://github.com/JamePeng/searxng_search/issues
Keywords: searxng,search-engine,local,lan,client,python
Classifier: Programming Language :: Python :: 3
Classifier: Operating System :: OS Independent
Classifier: Topic :: Internet :: WWW/HTTP :: Indexing/Search
Requires-Python: >=3.9
License-File: LICENSE.md
Requires-Dist: httpx>=0.23.0
Requires-Dist: lxml>=4.9.0
Dynamic: license-file
